{
  "unpublishedCollection": {
    "name": "RefreshTokenJS",
    "pageId": "Workorders",
    "pluginId": "js-plugin",
    "pluginType": "JS",
    "actions": [],
    "archivedActions": [],
    "variables": [
      {
        "name": "startTokenTime",
        "value": "0"
      },
      {
        "name": "startExpiresTokenJwt",
        "value": "0"
      }
    ],
    "userPermissions": []
  },
  "id": "Workorders_RefreshTokenJS",
  "deleted": false,
  "gitSyncId": "6502d1d5f3648a063724e3fe_65097f347473ff6ef432e1bd"
}